API/__init__.py
API/bmminer.py
API/bosminer.py
API/btminer.py
API/cgminer.py
API/unknown.py
config/__init__.py
config/bos.py
logger/__init__.py
miners/__init__.py
miners/bmminer.py
miners/bosminer.py
miners/btminer.py
miners/cgminer.py
miners/miner_factory.py
miners/unknown.py
miners/antminer/__init__.py
miners/antminer/S9/__init__.py
miners/antminer/S9/bmminer.py
miners/antminer/S9/bosminer.py
miners/antminer/S9/cgminer.py
miners/antminer/T9/__init__.py
miners/antminer/T9/bmminer.py
miners/antminer/T9/cgminer.py
miners/antminer/T9/hive.py
miners/antminer/X17/__init__.py
miners/antminer/X17/bmminer.py
miners/antminer/X17/bosminer.py
miners/antminer/X17/cgminer.py
miners/antminer/X19/__init__.py
miners/antminer/X19/bmminer.py
miners/antminer/X19/bosminer.py
miners/antminer/X19/cgminer.py
miners/avalonminer/__init__.py
miners/avalonminer/Avalon10/__init__.py
miners/avalonminer/Avalon8/__init__.py
miners/whatsminer/M20.py
miners/whatsminer/M21.py
miners/whatsminer/M30.py
miners/whatsminer/M31.py
miners/whatsminer/M32.py
miners/whatsminer/__init__.py
misc/__init__.py
misc/bos.py
network/__init__.py
network/net_range.py
settings/__init__.py
minerinterface-0.5.3.dist-info/METADATA
minerinterface-0.5.3.dist-info/WHEEL
minerinterface-0.5.3.dist-info/top_level.txt
minerinterface-0.5.3.dist-info/RECORD
